[{"id": 22, "user": "user8", "title": "LoadTest Alarm", "time": 1760315580}, {"id": 23, "user": "user42", "title": "LoadTest Alarm", "time": 1760315580}, {"id": 27, "user": "user19", "title": "LoadTest Alarm", "time": 1760315580}, {"id": 38, "user": "user12", "title": "LoadTest Alarm", "time": 1760315580}, {"id": 40, "user": "user33", "title": "LoadTest Alarm", "time": 1760315580}, {"id": 54, "user": "user11", "title": "LoadTest Alarm", "time": 1760315580}, {"id": 57, "user": "user36", "title": "LoadTest Alarm", "time": 1760315580}, {"id": 60, "user": "user27", "title": "LoadTest Alarm", "time": 1760315580}, {"id": 80, "user": "user30", "title": "LoadTest Alarm", "time": 1760315580}, {"id": 81, "user": "user16", "title": "LoadTest Alarm", "time": 1760315580}, {"id": 162, "user": "user1", "title": "LoadTest Alarm", "time": 1760229300}, {"id": 163, "user": "user19", "title": "LoadTest Alarm", "time": 1760229360}, {"id": 164, "user": "user45", "title": "LoadTest Alarm", "time": 1760229360}, {"id": 165, "user": "user4", "title": "LoadTest Alarm", "time": 1760229240}, {"id": 166, "user": "user15", "title": "LoadTest Alarm", "time": 1760229360}, {"id": 167, "user": "user40", "title": "LoadTest Alarm", "time": 1760229240}, {"id": 168, "user": "user46", "title": "LoadTest Alarm", "time": 1760229360}, {"id": 169, "user": "user2", "title": "LoadTest Alarm", "time": 1760229360}, {"id": 170, "user": "user22", "title": "LoadTest Alarm", "time": 1760229360}, {"id": 171, "user": "user3", "title": "LoadTest Alarm", "time": 1760229240}, {"id": 172, "user": "user4", "title": "LoadTest Alarm", "time": 1760229300}, {"id": 173, "user": "user33", "title": "LoadTest Alarm", "time": 1760229300}, {"id": 174, "user": "user22", "title": "LoadTest Alarm", "time": 1760229360}, {"id": 175, "user": "user36", "title": "LoadTest Alarm", "time": 1760229300}, {"id": 176, "user": "user41", "title": "LoadTest Alarm", "time": 1760315580}, {"id": 177, "user": "user42", "title": "LoadTest Alarm", "time": 1760229360}, {"id": 178, "user": "user42", "title": "LoadTest Alarm", "time": 1760229300}, {"id": 179, "user": "user19", "title": "LoadTest Alarm", "time": 1760229360}, {"id": 180, "user": "user28", "title": "LoadTest Alarm", "time": 1760229240}, {"id": 181, "user": "user13", "title": "LoadTest Alarm", "time": 1760229300}, {"id": 182, "user": "user2", "title": "LoadTest Alarm", "time": 1760229240}, {"id": 183, "user": "user12", "title": "LoadTest Alarm", "time": 1760229300}, {"id": 184, "user": "user47", "title": "LoadTest Alarm", "time": 1760229300}, {"id": 185, "user": "user15", "title": "LoadTest Alarm", "time": 1760229300}, {"id": 186, "user": "user8", "title": "LoadTest Alarm", "time": 1760229240}, {"id": 187, "user": "user50", "title": "LoadTest Alarm", "time": 1760229360}, {"id": 188, "user": "user42", "title": "LoadTest Alarm", "time": 1760229360}, {"id": 189, "user": "user24", "title": "LoadTest Alarm", "time": 1760229300}, {"id": 190, "user": "user8", "title": "LoadTest Alarm", "time": 1760229300}, {"id": 191, "user": "user23", "title": "LoadTest Alarm", "time": 1760229360}, {"id": 192, "user": "user4", "title": "LoadTest Alarm", "time": 1760229300}, {"id": 193, "user": "user33", "title": "LoadTest Alarm", "time": 1760229360}, {"id": 194, "user": "user18", "title": "LoadTest Alarm", "time": 1760229360}, {"id": 195, "user": "user24", "title": "LoadTest Alarm", "time": 1760229300}, {"id": 196, "user": "user48", "title": "LoadTest Alarm", "time": 1760315640}, {"id": 197, "user": "user8", "title": "LoadTest Alarm", "time": 1760229360}, {"id": 198, "user": "user27", "title": "LoadTest Alarm", "time": 1760315640}, {"id": 199, "user": "user49", "title": "LoadTest Alarm", "time": 1760229360}, {"id": 200, "user": "user27", "title": "LoadTest Alarm", "time": 1760229300}, {"id": 201, "user": "user40", "title": "LoadTest Alarm", "time": 1760229300}, {"id": 202, "user": "user30", "title": "LoadTest Alarm", "time": 1760315640}, {"id": 203, "user": "user23", "title": "LoadTest Alarm", "time": 1760229300}, {"id": 204, "user": "user33", "title": "LoadTest Alarm", "time": 1760229300}, {"id": 205, "user": "user31", "title": "LoadTest Alarm", "time": 1760229360}, {"id": 206, "user": "user23", "title": "LoadTest Alarm", "time": 1760229300}, {"id": 207, "user": "user36", "title": "LoadTest Alarm", "time": 1760229360}, {"id": 208, "user": "user35", "title": "LoadTest Alarm", "time": 1760315640}, {"id": 209, "user": "user1", "title": "LoadTest Alarm", "time": 1760315640}, {"id": 210, "user": "user7", "title": "LoadTest Alarm", "time": 1760229360}, {"id": 211, "user": "user16", "title": "LoadTest Alarm", "time": 1760229300}, {"id": 212, "user": "user32", "title": "LoadTest Alarm", "time": 1760315640}, {"id": 213, "user": "user4", "title": "LoadTest Alarm", "time": 1760229300}, {"id": 214, "user": "user9", "title": "LoadTest Alarm", "time": 1760229300}, {"id": 215, "user": "user3", "title": "LoadTest Alarm", "time": 1760229300}, {"id": 216, "user": "user2", "title": "LoadTest Alarm", "time": 1760315640}, {"id": 217, "user": "user26", "title": "LoadTest Alarm", "time": 1760315640}, {"id": 218, "user": "user8", "title": "LoadTest Alarm", "time": 1760229300}, {"id": 219, "user": "user10", "title": "LoadTest Alarm", "time": 1760229360}, {"id": 220, "user": "user26", "title": "LoadTest Alarm", "time": 1760229360}, {"id": 221, "user": "user3", "title": "LoadTest Alarm", "time": 1760229300}, {"id": 222, "user": "user43", "title": "LoadTest Alarm", "time": 1760229360}, {"id": 223, "user": "user46", "title": "LoadTest Alarm", "time": 1760229420}, {"id": 224, "user": "user36", "title": "LoadTest Alarm", "time": 1760315640}, {"id": 225, "user": "user24", "title": "LoadTest Alarm", "time": 1760315640}, {"id": 226, "user": "user20", "title": "LoadTest Alarm", "time": 1760229300}, {"id": 227, "user": "user21", "title": "LoadTest Alarm", "time": 1760229360}, {"id": 228, "user": "user50", "title": "LoadTest Alarm", "time": 1760229360}, {"id": 229, "user": "user24", "title": "LoadTest Alarm", "time": 1760315640}, {"id": 230, "user": "user13", "title": "LoadTest Alarm", "time": 1760315640}, {"id": 231, "user": "user36", "title": "LoadTest Alarm", "time": 1760229300}, {"id": 232, "user": "user42", "title": "LoadTest Alarm", "time": 1760229300}, {"id": 233, "user": "user40", "title": "LoadTest Alarm", "time": 1760229360}, {"id": 234, "user": "user8", "title": "LoadTest Alarm", "time": 1760229360}, {"id": 235, "user": "user6", "title": "LoadTest Alarm", "time": 1760229300}, {"id": 236, "user": "user1", "title": "LoadTest Alarm", "time": 1760315640}, {"id": 237, "user": "user41", "title": "LoadTest Alarm", "time": 1760315640}, {"id": 238, "user": "user36", "title": "LoadTest Alarm", "time": 1760229360}, {"id": 239, "user": "user16", "title": "LoadTest Alarm", "time": 1760229300}, {"id": 240, "user": "user45", "title": "LoadTest Alarm", "time": 1760229360}, {"id": 241, "user": "user8", "title": "LoadTest Alarm", "time": 1760229360}, {"id": 242, "user": "user42", "title": "LoadTest Alarm", "time": 1760229300}, {"id": 243, "user": "user32", "title": "LoadTest Alarm", "time": 1760229360}, {"id": 244, "user": "user32", "title": "LoadTest Alarm", "time": 1760229300}, {"id": 245, "user": "user42", "title": "LoadTest Alarm", "time": 1760229300}, {"id": 246, "user": "user33", "title": "LoadTest Alarm", "time": 1760229300}, {"id": 247, "user": "user19", "title": "LoadTest Alarm", "time": 1760229360}, {"id": 248, "user": "user21", "title": "LoadTest Alarm", "time": 1760229300}, {"id": 249, "user": "user3", "title": "LoadTest Alarm", "time": 1760315640}, {"id": 250, "user": "user15", "title": "LoadTest Alarm", "time": 1760229300}, {"id": 251, "user": "user19", "title": "LoadTest Alarm", "time": 1760229300}, {"id": 252, "user": "user9", "title": "LoadTest Alarm", "time": 1760315640}, {"id": 253, "user": "user45", "title": "LoadTest Alarm", "time": 1760229360}, {"id": 254, "user": "user20", "title": "LoadTest Alarm", "time": 1760315640}, {"id": 255, "user": "user2", "title": "LoadTest Alarm", "time": 1760315640}, {"id": 256, "user": "user50", "title": "LoadTest Alarm", "time": 1760229300}, {"id": 257, "user": "user20", "title": "LoadTest Alarm", "time": 1760315640}, {"id": 258, "user": "user15", "title": "LoadTest Alarm", "time": 1760229300}, {"id": 259, "user": "user22", "title": "LoadTest Alarm", "time": 1760229300}, {"id": 260, "user": "user50", "title": "LoadTest Alarm", "time": 1760315640}, {"id": 261, "user": "user45", "title": "LoadTest Alarm", "time": 1760229300}, {"id": 262, "user": "user18", "title": "LoadTest Alarm", "time": 1760229300}, {"id": 263, "user": "user32", "title": "LoadTest Alarm", "time": 1760229300}, {"id": 264, "user": "user28", "title": "LoadTest Alarm", "time": 1760229360}, {"id": 265, "user": "user36", "title": "LoadTest Alarm", "time": 1760229300}, {"id": 266, "user": "user47", "title": "LoadTest Alarm", "time": 1760229360}, {"id": 267, "user": "user47", "title": "LoadTest Alarm", "time": 1760229300}, {"id": 268, "user": "user33", "title": "LoadTest Alarm", "time": 1760229300}, {"id": 269, "user": "user19", "title": "LoadTest Alarm", "time": 1760229300}, {"id": 270, "user": "user45", "title": "LoadTest Alarm", "time": 1760315640}, {"id": 271, "user": "user38", "title": "LoadTest Alarm", "time": 1760229300}, {"id": 272, "user": "user31", "title": "LoadTest Alarm", "time": 1760229300}, {"id": 273, "user": "user33", "title": "LoadTest Alarm", "time": 1760229360}, {"id": 274, "user": "user8", "title": "LoadTest Alarm", "time": 1760229360}, {"id": 275, "user": "user24", "title": "LoadTest Alarm", "time": 1760229300}, {"id": 276, "user": "user32", "title": "LoadTest Alarm", "time": 1760229360}, {"id": 277, "user": "user23", "title": "LoadTest Alarm", "time": 1760229360}, {"id": 278, "user": "user24", "title": "LoadTest Alarm", "time": 1760229360}, {"id": 279, "user": "user3", "title": "LoadTest Alarm", "time": 1760229420}, {"id": 280, "user": "user29", "title": "LoadTest Alarm", "time": 1760229360}, {"id": 281, "user": "user26", "title": "LoadTest Alarm", "time": 1760229300}, {"id": 282, "user": "user22", "title": "LoadTest Alarm", "time": 1760229300}, {"id": 283, "user": "user36", "title": "LoadTest Alarm", "time": 1760229360}, {"id": 284, "user": "user1", "title": "LoadTest Alarm", "time": 1760229360}, {"id": 285, "user": "user31", "title": "LoadTest Alarm", "time": 1760229360}, {"id": 286, "user": "user22", "title": "LoadTest Alarm", "time": 1760315640}, {"id": 287, "user": "user50", "title": "LoadTest Alarm", "time": 1760229300}, {"id": 288, "user": "user27", "title": "LoadTest Alarm", "time": 1760229300}, {"id": 289, "user": "user36", "title": "LoadTest Alarm", "time": 1760315640}, {"id": 290, "user": "user8", "title": "LoadTest Alarm", "time": 1760229300}, {"id": 291, "user": "user43", "title": "LoadTest Alarm", "time": 1760229360}, {"id": 292, "user": "user16", "title": "LoadTest Alarm", "time": 1760229300}, {"id": 293, "user": "user33", "title": "LoadTest Alarm", "time": 1760315640}, {"id": 294, "user": "user44", "title": "LoadTest Alarm", "time": 1760315640}, {"id": 295, "user": "user11", "title": "LoadTest Alarm", "time": 1760229300}, {"id": 296, "user": "user16", "title": "LoadTest Alarm", "time": 1760229360}, {"id": 297, "user": "user2", "title": "LoadTest Alarm", "time": 1760229360}, {"id": 298, "user": "user45", "title": "LoadTest Alarm", "time": 1760229300}, {"id": 299, "user": "user28", "title": "LoadTest Alarm", "time": 1760229360}, {"id": 300, "user": "user48", "title": "LoadTest Alarm", "time": 1760229300}, {"id": 301, "user": "user15", "title": "LoadTest Alarm", "time": 1760315640}, {"id": 302, "user": "user42", "title": "LoadTest Alarm", "time": 1760229360}, {"id": 303, "user": "user33", "title": "LoadTest Alarm", "time": 1760229360}, {"id": 304, "user": "user50", "title": "LoadTest Alarm", "time": 1760229360}, {"id": 305, "user": "user32", "title": "LoadTest Alarm", "time": 1760229300}, {"id": 306, "user": "user12", "title": "LoadTest Alarm", "time": 1760229300}, {"id": 307, "user": "user36", "title": "LoadTest Alarm", "time": 1760315640}, {"id": 308, "user": "user15", "title": "LoadTest Alarm", "time": 1760229300}, {"id": 309, "user": "user9", "title": "LoadTest Alarm", "time": 1760229300}, {"id": 310, "user": "user47", "title": "LoadTest Alarm", "time": 1760229360}, {"id": 311, "user": "user14", "title": "LoadTest Alarm", "time": 1760229360}, {"id": 312, "user": "user10", "title": "LoadTest Alarm", "time": 1760315640}, {"id": 313, "user": "user18", "title": "LoadTest Alarm", "time": 1760229300}, {"id": 314, "user": "user42", "title": "LoadTest Alarm", "time": 1760229360}, {"id": 315, "user": "user11", "title": "LoadTest Alarm", "time": 1760229300}, {"id": 316, "user": "user33", "title": "LoadTest Alarm", "time": 1760229360}, {"id": 317, "user": "user26", "title": "LoadTest Alarm", "time": 1760315640}, {"id": 318, "user": "user31", "title": "LoadTest Alarm", "time": 1760229360}, {"id": 319, "user": "user29", "title": "LoadTest Alarm", "time": 1760315640}, {"id": 320, "user": "user16", "title": "LoadTest Alarm", "time": 1760229420}, {"id": 321, "user": "user24", "title": "LoadTest Alarm", "time": 1760229300}, {"id": 322, "user": "user23", "title": "LoadTest Alarm", "time": 1760229360}, {"id": 323, "user": "user32", "title": "LoadTest Alarm", "time": 1760229300}, {"id": 324, "user": "user36", "title": "LoadTest Alarm", "time": 1760229300}, {"id": 325, "user": "user41", "title": "LoadTest Alarm", "time": 1760229420}, {"id": 326, "user": "user35", "title": "LoadTest Alarm", "time": 1760229300}, {"id": 327, "user": "user16", "title": "LoadTest Alarm", "time": 1760229420}, {"id": 328, "user": "user45", "title": "LoadTest Alarm", "time": 1760229420}, {"id": 329, "user": "user12", "title": "LoadTest Alarm", "time": 1760229300}, {"id": 330, "user": "user38", "title": "LoadTest Alarm", "time": 1760315640}, {"id": 331, "user": "user4", "title": "LoadTest Alarm", "time": 1760229360}, {"id": 332, "user": "user19", "title": "LoadTest Alarm", "time": 1760229300}, {"id": 333, "user": "user13", "title": "LoadTest Alarm", "time": 1760229360}, {"id": 334, "user": "user50", "title": "LoadTest Alarm", "time": 1760315640}, {"id": 335, "user": "user2", "title": "LoadTest Alarm", "time": 1760229360}, {"id": 336, "user": "user36", "title": "LoadTest Alarm", "time": 1760315640}, {"id": 337, "user": "user19", "title": "LoadTest Alarm", "time": 1760229420}, {"id": 338, "user": "user46", "title": "LoadTest Alarm", "time": 1760229420}, {"id": 339, "user": "user16", "title": "LoadTest Alarm", "time": 1760229360}, {"id": 340, "user": "user7", "title": "LoadTest Alarm", "time": 1760229360}, {"id": 341, "user": "user8", "title": "LoadTest Alarm", "time": 1760229420}, {"id": 342, "user": "user24", "title": "LoadTest Alarm", "time": 1760315640}, {"id": 343, "user": "user33", "title": "LoadTest Alarm", "time": 1760229360}, {"id": 344, "user": "user1", "title": "LoadTest Alarm", "time": 1760229300}, {"id": 345, "user": "user32", "title": "LoadTest Alarm", "time": 1760229300}, {"id": 346, "user": "user47", "title": "LoadTest Alarm", "time": 1760229420}, {"id": 347, "user": "user20", "title": "LoadTest Alarm", "time": 1760229300}, {"id": 348, "user": "user42", "title": "LoadTest Alarm", "time": 1760229300}, {"id": 349, "user": "user20", "title": "LoadTest Alarm", "time": 1760229420}, {"id": 350, "user": "user12", "title": "LoadTest Alarm", "time": 1760229300}, {"id": 351, "user": "user36", "title": "LoadTest Alarm", "time": 1760229420}, {"id": 352, "user": "user5", "title": "LoadTest Alarm", "time": 1760229360}, {"id": 353, "user": "user42", "title": "LoadTest Alarm", "time": 1760229420}, {"id": 354, "user": "user44", "title": "LoadTest Alarm", "time": 1760229360}, {"id": 355, "user": "user41", "title": "LoadTest Alarm", "time": 1760229360}, {"id": 356, "user": "user46", "title": "LoadTest Alarm", "time": 1760229360}, {"id": 357, "user": "user8", "title": "LoadTest Alarm", "time": 1760229300}, {"id": 358, "user": "user36", "title": "LoadTest Alarm", "time": 1760229360}, {"id": 359, "user": "user42", "title": "LoadTest Alarm", "time": 1760315640}, {"id": 360, "user": "user43", "title": "LoadTest Alarm", "time": 1760229360}, {"id": 361, "user": "user31", "title": "LoadTest Alarm", "time": 1760229360}, {"id": 362, "user": "user40", "title": "LoadTest Alarm", "time": 1760315640}, {"id": 363, "user": "user32", "title": "LoadTest Alarm", "time": 1760229300}, {"id": 364, "user": "user10", "title": "LoadTest Alarm", "time": 1760229360}, {"id": 365, "user": "user13", "title": "LoadTest Alarm", "time": 1760315640}, {"id": 366, "user": "user47", "title": "LoadTest Alarm", "time": 1760315640}, {"id": 367, "user": "user23", "title": "LoadTest Alarm", "time": 1760315640}, {"id": 368, "user": "user23", "title": "LoadTest Alarm", "time": 1760229420}, {"id": 369, "user": "user40", "title": "LoadTest Alarm", "time": 1760315640}, {"id": 370, "user": "user3", "title": "LoadTest Alarm", "time": 1760229360}, {"id": 371, "user": "user41", "title": "LoadTest Alarm", "time": 1760229360}, {"id": 372, "user": "user45", "title": "LoadTest Alarm", "time": 1760229360}, {"id": 373, "user": "user35", "title": "LoadTest Alarm", "time": 1760315640}, {"id": 374, "user": "user18", "title": "LoadTest Alarm", "time": 1760229360}, {"id": 375, "user": "user35", "title": "LoadTest Alarm", "time": 1760229360}, {"id": 376, "user": "user23", "title": "LoadTest Alarm", "time": 1760229420}, {"id": 377, "user": "user16", "title": "LoadTest Alarm", "time": 1760229300}, {"id": 378, "user": "user20", "title": "LoadTest Alarm", "time": 1760229300}, {"id": 379, "user": "user4", "title": "LoadTest Alarm", "time": 1760315640}, {"id": 380, "user": "user41", "title": "LoadTest Alarm", "time": 1760229420}, {"id": 381, "user": "user13", "title": "LoadTest Alarm", "time": 1760315640}, {"id": 382, "user": "user10", "title": "LoadTest Alarm", "time": 1760229360}, {"id": 383, "user": "user21", "title": "LoadTest Alarm", "time": 1760229360}, {"id": 384, "user": "user43", "title": "LoadTest Alarm", "time": 1760315640}, {"id": 385, "user": "user16", "title": "LoadTest Alarm", "time": 1760229360}, {"id": 386, "user": "user25", "title": "LoadTest Alarm", "time": 1760229360}, {"id": 387, "user": "user41", "title": "LoadTest Alarm", "time": 1760229420}, {"id": 388, "user": "user49", "title": "LoadTest Alarm", "time": 1760315640}, {"id": 389, "user": "user28", "title": "LoadTest Alarm", "time": 1760229360}, {"id": 390, "user": "user50", "title": "LoadTest Alarm", "time": 1760229360}, {"id": 391, "user": "user42", "title": "LoadTest Alarm", "time": 1760229360}, {"id": 392, "user": "user42", "title": "LoadTest Alarm", "time": 1760229420}, {"id": 393, "user": "user31", "title": "LoadTest Alarm", "time": 1760229360}, {"id": 394, "user": "user24", "title": "LoadTest Alarm", "time": 1760315640}, {"id": 395, "user": "user7", "title": "LoadTest Alarm", "time": 1760315640}, {"id": 396, "user": "user8", "title": "LoadTest Alarm", "time": 1760229300}, {"id": 397, "user": "user22", "title": "LoadTest Alarm", "time": 1760229360}, {"id": 398, "user": "user5", "title": "LoadTest Alarm", "time": 1760229360}, {"id": 399, "user": "user4", "title": "LoadTest Alarm", "time": 1760229360}, {"id": 400, "user": "user10", "title": "LoadTest Alarm", "time": 1760315640}, {"id": 401, "user": "user33", "title": "LoadTest Alarm", "time": 1760229360}, {"id": 402, "user": "user44", "title": "LoadTest Alarm", "time": 1760229360}, {"id": 403, "user": "user19", "title": "LoadTest Alarm", "time": 1760229300}, {"id": 404, "user": "user18", "title": "LoadTest Alarm", "time": 1760229420}, {"id": 405, "user": "user46", "title": "LoadTest Alarm", "time": 1760229420}, {"id": 406, "user": "user4", "title": "LoadTest Alarm", "time": 1760229360}, {"id": 407, "user": "user4", "title": "LoadTest Alarm", "time": 1760229420}, {"id": 408, "user": "user32", "title": "LoadTest Alarm", "time": 1760229360}, {"id": 409, "user": "user24", "title": "LoadTest Alarm", "time": 1760315640}, {"id": 410, "user": "user31", "title": "LoadTest Alarm", "time": 1760229300}, {"id": 411, "user": "user34", "title": "LoadTest Alarm", "time": 1760229360}, {"id": 412, "user": "user29", "title": "LoadTest Alarm", "time": 1760229420}, {"id": 413, "user": "user45", "title": "LoadTest Alarm", "time": 1760229360}, {"id": 414, "user": "user38", "title": "LoadTest Alarm", "time": 1760315640}, {"id": 415, "user": "user40", "title": "LoadTest Alarm", "time": 1760229360}, {"id": 416, "user": "user1", "title": "LoadTest Alarm", "time": 1760229420}, {"id": 417, "user": "user26", "title": "LoadTest Alarm", "time": 1760229360}, {"id": 418, "user": "user4", "title": "LoadTest Alarm", "time": 1760229420}, {"id": 419, "user": "user31", "title": "LoadTest Alarm", "time": 1760229360}, {"id": 420, "user": "user6", "title": "LoadTest Alarm", "time": 1760229420}, {"id": 421, "user": "user23", "title": "LoadTest Alarm", "time": 1760315640}, {"id": 422, "user": "user18", "title": "LoadTest Alarm", "time": 1760229300}, {"id": 423, "user": "user41", "title": "LoadTest Alarm", "time": 1760229360}, {"id": 424, "user": "user46", "title": "LoadTest Alarm", "time": 1760315640}, {"id": 425, "user": "user49", "title": "LoadTest Alarm", "time": 1760229360}, {"id": 426, "user": "user40", "title": "LoadTest Alarm", "time": 1760229360}, {"id": 427, "user": "user50", "title": "LoadTest Alarm", "time": 1760315640}, {"id": 428, "user": "user41", "title": "LoadTest Alarm", "time": 1760229300}, {"id": 429, "user": "user30", "title": "LoadTest Alarm", "time": 1760229360}, {"id": 430, "user": "user41", "title": "LoadTest Alarm", "time": 1760229360}, {"id": 431, "user": "user40", "title": "LoadTest Alarm", "time": 1760229300}, {"id": 432, "user": "user35", "title": "LoadTest Alarm", "time": 1760229300}, {"id": 433, "user": "user36", "title": "LoadTest Alarm", "time": 1760229300}, {"id": 434, "user": "user41", "title": "LoadTest Alarm", "time": 1760315640}, {"id": 435, "user": "user36", "title": "LoadTest Alarm", "time": 1760229420}, {"id": 436, "user": "user24", "title": "LoadTest Alarm", "time": 1760229420}, {"id": 437, "user": "user24", "title": "LoadTest Alarm", "time": 1760315640}, {"id": 438, "user": "user30", "title": "LoadTest Alarm", "time": 1760229300}, {"id": 439, "user": "user2", "title": "LoadTest Alarm", "time": 1760229300}, {"id": 440, "user": "user45", "title": "LoadTest Alarm", "time": 1760229300}, {"id": 441, "user": "user36", "title": "LoadTest Alarm", "time": 1760315640}, {"id": 442, "user": "user35", "title": "LoadTest Alarm", "time": 1760315640}, {"id": 443, "user": "user8", "title": "LoadTest Alarm", "time": 1760229360}, {"id": 444, "user": "user4", "title": "LoadTest Alarm", "time": 1760229360}, {"id": 445, "user": "user3", "title": "LoadTest Alarm", "time": 1760229420}, {"id": 446, "user": "user1", "title": "LoadTest Alarm", "time": 1760229360}, {"id": 447, "user": "user36", "title": "LoadTest Alarm", "time": 1760229360}, {"id": 448, "user": "user42", "title": "LoadTest Alarm", "time": 1760229360}, {"id": 449, "user": "user19", "title": "LoadTest Alarm", "time": 1760229360}, {"id": 450, "user": "user36", "title": "LoadTest Alarm", "time": 1760315640}, {"id": 451, "user": "user2", "title": "LoadTest Alarm", "time": 1760229300}, {"id": 452, "user": "user42", "title": "LoadTest Alarm", "time": 1760315640}, {"id": 453, "user": "user44", "title": "LoadTest Alarm", "time": 1760315640}, {"id": 454, "user": "user50", "title": "LoadTest Alarm", "time": 1760229360}, {"id": 455, "user": "user8", "title": "LoadTest Alarm", "time": 1760315640}, {"id": 456, "user": "user19", "title": "LoadTest Alarm", "time": 1760229360}, {"id": 457, "user": "user16", "title": "LoadTest Alarm", "time": 1760229420}, {"id": 458, "user": "user9", "title": "LoadTest Alarm", "time": 1760229420}, {"id": 459, "user": "user24", "title": "LoadTest Alarm", "time": 1760229300}, {"id": 460, "user": "user15", "title": "LoadTest Alarm", "time": 1760229300}, {"id": 461, "user": "user4", "title": "LoadTest Alarm", "time": 1760315640}, {"id": 462, "user": "user33", "title": "LoadTest Alarm", "time": 1760315640}, {"id": 463, "user": "user30", "title": "LoadTest Alarm", "time": 1760229360}, {"id": 464, "user": "user20", "title": "LoadTest Alarm", "time": 1760229300}, {"id": 465, "user": "user23", "title": "LoadTest Alarm", "time": 1760229360}, {"id": 466, "user": "user23", "title": "LoadTest Alarm", "time": 1760229360}, {"id": 467, "user": "user2", "title": "LoadTest Alarm", "time": 1760229420}, {"id": 468, "user": "user42", "title": "LoadTest Alarm", "time": 1760229420}, {"id": 469, "user": "user4", "title": "LoadTest Alarm", "time": 1760229300}, {"id": 470, "user": "user40", "title": "LoadTest Alarm", "time": 1760229300}, {"id": 471, "user": "user16", "title": "LoadTest Alarm", "time": 1760229300}, {"id": 472, "user": "user40", "title": "LoadTest Alarm", "time": 1760229300}, {"id": 473, "user": "user2", "title": "LoadTest Alarm", "time": 1760229420}, {"id": 474, "user": "user43", "title": "LoadTest Alarm", "time": 1760229420}, {"id": 475, "user": "user19", "title": "LoadTest Alarm", "time": 1760315640}, {"id": 476, "user": "user22", "title": "LoadTest Alarm", "time": 1760229360}, {"id": 477, "user": "user6", "title": "LoadTest Alarm", "time": 1760229360}, {"id": 478, "user": "user42", "title": "LoadTest Alarm", "time": 1760229300}, {"id": 479, "user": "user42", "title": "LoadTest Alarm", "time": 1760229300}, {"id": 480, "user": "user10", "title": "LoadTest Alarm", "time": 1760229420}, {"id": 481, "user": "user36", "title": "LoadTest Alarm", "time": 1760229360}, {"id": 482, "user": "user10", "title": "LoadTest Alarm", "time": 1760229300}, {"id": 483, "user": "user43", "title": "LoadTest Alarm", "time": 1760229420}, {"id": 484, "user": "user41", "title": "LoadTest Alarm", "time": 1760229300}, {"id": 485, "user": "user42", "title": "LoadTest Alarm", "time": 1760315640}, {"id": 486, "user": "user23", "title": "LoadTest Alarm", "time": 1760229360}, {"id": 487, "user": "user24", "title": "LoadTest Alarm", "time": 1760229300}, {"id": 488, "user": "user45", "title": "LoadTest Alarm", "time": 1760229360}, {"id": 489, "user": "user16", "title": "LoadTest Alarm", "time": 1760229420}, {"id": 490, "user": "user19", "title": "LoadTest Alarm", "time": 1760229300}, {"id": 491, "user": "user21", "title": "LoadTest Alarm", "time": 1760229300}, {"id": 492, "user": "user12", "title": "LoadTest Alarm", "time": 1760315640}, {"id": 493, "user": "user31", "title": "LoadTest Alarm", "time": 1760229360}, {"id": 494, "user": "user44", "title": "LoadTest Alarm", "time": 1760229300}, {"id": 495, "user": "user36", "title": "LoadTest Alarm", "time": 1760229360}, {"id": 496, "user": "user30", "title": "LoadTest Alarm", "time": 1760229420}, {"id": 497, "user": "user8", "title": "LoadTest Alarm", "time": 1760229300}, {"id": 498, "user": "user30", "title": "LoadTest Alarm", "time": 1760229300}, {"id": 499, "user": "user8", "title": "LoadTest Alarm", "time": 1760229420}, {"id": 500, "user": "user27", "title": "LoadTest Alarm", "time": 1760229360}, {"id": 501, "user": "user15", "title": "LoadTest Alarm", "time": 1760229420}, {"id": 502, "user": "user21", "title": "LoadTest Alarm", "time": 1760229300}, {"id": 503, "user": "user34", "title": "LoadTest Alarm", "time": 1760229420}, {"id": 504, "user": "user4", "title": "LoadTest Alarm", "time": 1760229360}, {"id": 505, "user": "user12", "title": "LoadTest Alarm", "time": 1760229300}, {"id": 506, "user": "user1", "title": "LoadTest Alarm", "time": 1760229420}, {"id": 507, "user": "user2", "title": "LoadTest Alarm", "time": 1760229420}, {"id": 508, "user": "user36", "title": "LoadTest Alarm", "time": 1760229300}, {"id": 509, "user": "user16", "title": "LoadTest Alarm", "time": 1760229300}, {"id": 510, "user": "user2", "title": "LoadTest Alarm", "time": 1760229420}, {"id": 511, "user": "user42", "title": "LoadTest Alarm", "time": 1760229420}, {"id": 512, "user": "user1", "title": "LoadTest Alarm", "time": 1760229420}, {"id": 513, "user": "user13", "title": "LoadTest Alarm", "time": 1760229420}, {"id": 514, "user": "user43", "title": "LoadTest Alarm", "time": 1760229300}, {"id": 515, "user": "user42", "title": "LoadTest Alarm", "time": 1760229420}, {"id": 516, "user": "user38", "title": "LoadTest Alarm", "time": 1760229300}, {"id": 517, "user": "user35", "title": "LoadTest Alarm", "time": 1760229420}, {"id": 518, "user": "user16", "title": "LoadTest Alarm", "time": 1760229360}, {"id": 519, "user": "user42", "title": "LoadTest Alarm", "time": 1760229420}, {"id": 520, "user": "user14", "title": "LoadTest Alarm", "time": 1760229300}, {"id": 521, "user": "user36", "title": "LoadTest Alarm", "time": 1760229360}, {"id": 522, "user": "user6", "title": "LoadTest Alarm", "time": 1760229360}, {"id": 523, "user": "user12", "title": "LoadTest Alarm", "time": 1760229300}, {"id": 524, "user": "user44", "title": "LoadTest Alarm", "time": 1760229300}, {"id": 525, "user": "user43", "title": "LoadTest Alarm", "time": 1760229360}, {"id": 526, "user": "user50", "title": "LoadTest Alarm", "time": 1760229420}, {"id": 527, "user": "user35", "title": "LoadTest Alarm", "time": 1760229300}, {"id": 528, "user": "user32", "title": "LoadTest Alarm", "time": 1760229420}, {"id": 529, "user": "user35", "title": "LoadTest Alarm", "time": 1760229300}, {"id": 530, "user": "user36", "title": "LoadTest Alarm", "time": 1760229300}, {"id": 531, "user": "user22", "title": "LoadTest Alarm", "time": 1760229300}, {"id": 532, "user": "user12", "title": "LoadTest Alarm", "time": 1760229300}, {"id": 533, "user": "user49", "title": "LoadTest Alarm", "time": 1760229300}, {"id": 534, "user": "user43", "title": "LoadTest Alarm", "time": 1760229300}, {"id": 535, "user": "user30", "title": "LoadTest Alarm", "time": 1760229360}, {"id": 536, "user": "user13", "title": "LoadTest Alarm", "time": 1760229420}, {"id": 537, "user": "user36", "title": "LoadTest Alarm", "time": 1760229360}, {"id": 538, "user": "user45", "title": "LoadTest Alarm", "time": 1760229360}, {"id": 539, "user": "user29", "title": "LoadTest Alarm", "time": 1760229360}, {"id": 540, "user": "user32", "title": "LoadTest Alarm", "time": 1760229360}, {"id": 541, "user": "user33", "title": "LoadTest Alarm", "time": 1760315700}, {"id": 542, "user": "user1", "title": "LoadTest Alarm", "time": 1760315700}, {"id": 543, "user": "user50", "title": "LoadTest Alarm", "time": 1760229420}, {"id": 544, "user": "user49", "title": "LoadTest Alarm", "time": 1760229420}, {"id": 545, "user": "user47", "title": "LoadTest Alarm", "time": 1760315700}, {"id": 546, "user": "user2", "title": "LoadTest Alarm", "time": 1760229360}, {"id": 547, "user": "user2", "title": "LoadTest Alarm", "time": 1760229420}, {"id": 548, "user": "user5", "title": "LoadTest Alarm", "time": 1760229360}, {"id": 549, "user": "user36", "title": "LoadTest Alarm", "time": 1760315700}, {"id": 550, "user": "user40", "title": "LoadTest Alarm", "time": 1760229360}, {"id": 551, "user": "user42", "title": "LoadTest Alarm", "time": 1760229420}, {"id": 552, "user": "user9", "title": "LoadTest Alarm", "time": 1760315700}, {"id": 553, "user": "user7", "title": "LoadTest Alarm", "time": 1760315700}, {"id": 554, "user": "user32", "title": "LoadTest Alarm", "time": 1760229360}, {"id": 555, "user": "user13", "title": "LoadTest Alarm", "time": 1760315700}, {"id": 556, "user": "user28", "title": "LoadTest Alarm", "time": 1760315700}, {"id": 557, "user": "user4", "title": "LoadTest Alarm", "time": 1760315700}, {"id": 558, "user": "user8", "title": "LoadTest Alarm", "time": 1760229360}, {"id": 559, "user": "user41", "title": "LoadTest Alarm", "time": 1760229420}, {"id": 560, "user": "user23", "title": "LoadTest Alarm", "time": 1760315700}, {"id": 561, "user": "user42", "title": "LoadTest Alarm", "time": 1760315700}, {"id": 562, "user": "user48", "title": "LoadTest Alarm", "time": 1760229420}, {"id": 563, "user": "user25", "title": "LoadTest Alarm", "time": 1760315700}, {"id": 564, "user": "user45", "title": "LoadTest Alarm", "time": 1760315700}, {"id": 565, "user": "user50", "title": "LoadTest Alarm", "time": 1760229360}, {"id": 566, "user": "user33", "title": "LoadTest Alarm", "time": 1760315700}, {"id": 567, "user": "user36", "title": "LoadTest Alarm", "time": 1760229360}, {"id": 568, "user": "user33", "title": "LoadTest Alarm", "time": 1760229420}, {"id": 569, "user": "user10", "title": "LoadTest Alarm", "time": 1760229360}, {"id": 570, "user": "user20", "title": "LoadTest Alarm", "time": 1760229420}, {"id": 571, "user": "user42", "title": "LoadTest Alarm", "time": 1760315700}, {"id": 572, "user": "user23", "title": "LoadTest Alarm", "time": 1760315700}, {"id": 573, "user": "user38", "title": "LoadTest Alarm", "time": 1760315700}, {"id": 574, "user": "user47", "title": "LoadTest Alarm", "time": 1760315700}, {"id": 575, "user": "user8", "title": "LoadTest Alarm", "time": 1760229360}, {"id": 576, "user": "user8", "title": "LoadTest Alarm", "time": 1760229360}, {"id": 577, "user": "user28", "title": "LoadTest Alarm", "time": 1760315700}, {"id": 578, "user": "user19", "title": "LoadTest Alarm", "time": 1760229420}, {"id": 579, "user": "user1", "title": "LoadTest Alarm", "time": 1760229420}, {"id": 580, "user": "user8", "title": "LoadTest Alarm", "time": 1760229420}, {"id": 581, "user": "user36", "title": "LoadTest Alarm", "time": 1760315700}, {"id": 582, "user": "user43", "title": "LoadTest Alarm", "time": 1760315700}, {"id": 583, "user": "user41", "title": "LoadTest Alarm", "time": 1760315700}, {"id": 584, "user": "user42", "title": "LoadTest Alarm", "time": 1760315700}, {"id": 585, "user": "user13", "title": "LoadTest Alarm", "time": 1760229420}, {"id": 586, "user": "user41", "title": "LoadTest Alarm", "time": 1760315700}, {"id": 587, "user": "user1", "title": "LoadTest Alarm", "time": 1760229420}, {"id": 588, "user": "user16", "title": "LoadTest Alarm", "time": 1760315700}, {"id": 589, "user": "user42", "title": "LoadTest Alarm", "time": 1760229420}, {"id": 590, "user": "user7", "title": "LoadTest Alarm", "time": 1760229360}, {"id": 591, "user": "user4", "title": "LoadTest Alarm", "time": 1760315700}, {"id": 592, "user": "user19", "title": "LoadTest Alarm", "time": 1760229420}, {"id": 593, "user": "user22", "title": "LoadTest Alarm", "time": 1760229420}, {"id": 594, "user": "user34", "title": "LoadTest Alarm", "time": 1760315700}, {"id": 595, "user": "user36", "title": "LoadTest Alarm", "time": 1760229360}, {"id": 596, "user": "user31", "title": "LoadTest Alarm", "time": 1760229360}, {"id": 597, "user": "user28", "title": "LoadTest Alarm", "time": 1760229360}, {"id": 598, "user": "user38", "title": "LoadTest Alarm", "time": 1760229420}, {"id": 599, "user": "user49", "title": "LoadTest Alarm", "time": 1760315700}, {"id": 600, "user": "user10", "title": "LoadTest Alarm", "time": 1760229360}, {"id": 601, "user": "user16", "title": "LoadTest Alarm", "time": 1760229420}, {"id": 602, "user": "user18", "title": "LoadTest Alarm", "time": 1760229420}, {"id": 603, "user": "user23", "title": "LoadTest Alarm", "time": 1760229420}, {"id": 604, "user": "user23", "title": "LoadTest Alarm", "time": 1760315700}, {"id": 605, "user": "user30", "title": "LoadTest Alarm", "time": 1760229360}, {"id": 606, "user": "user27", "title": "LoadTest Alarm", "time": 1760229360}, {"id": 607, "user": "user24", "title": "LoadTest Alarm", "time": 1760229360}, {"id": 608, "user": "user27", "title": "LoadTest Alarm", "time": 1760315700}, {"id": 609, "user": "user41", "title": "LoadTest Alarm", "time": 1760229420}, {"id": 610, "user": "user5", "title": "LoadTest Alarm", "time": 1760229360}, {"id": 611, "user": "user41", "title": "LoadTest Alarm", "time": 1760229420}, {"id": 612, "user": "user36", "title": "LoadTest Alarm", "time": 1760229360}, {"id": 613, "user": "user8", "title": "LoadTest Alarm", "time": 1760229360}, {"id": 614, "user": "user12", "title": "LoadTest Alarm", "time": 1760229420}, {"id": 615, "user": "user42", "title": "LoadTest Alarm", "time": 1760229360}, {"id": 616, "user": "user21", "title": "LoadTest Alarm", "time": 1760315700}, {"id": 617, "user": "user24", "title": "LoadTest Alarm", "time": 1760229420}, {"id": 618, "user": "user34", "title": "LoadTest Alarm", "time": 1760315700}, {"id": 619, "user": "user23", "title": "LoadTest Alarm", "time": 1760229480}, {"id": 620, "user": "user49", "title": "LoadTest Alarm", "time": 1760315700}, {"id": 621, "user": "user32", "title": "LoadTest Alarm", "time": 1760229420}, {"id": 622, "user": "user48", "title": "LoadTest Alarm", "time": 1760229420}, {"id": 623, "user": "user24", "title": "LoadTest Alarm", "time": 1760229480}, {"id": 624, "user": "user14", "title": "LoadTest Alarm", "time": 1760229360}, {"id": 625, "user": "user15", "title": "LoadTest Alarm", "time": 1760229420}, {"id": 626, "user": "user34", "title": "LoadTest Alarm", "time": 1760229360}, {"id": 627, "user": "user19", "title": "LoadTest Alarm", "time": 1760229420}, {"id": 628, "user": "user18", "title": "LoadTest Alarm", "time": 1760229360}, {"id": 629, "user": "user23", "title": "LoadTest Alarm", "time": 1760229420}, {"id": 630, "user": "user47", "title": "LoadTest Alarm", "time": 1760229360}, {"id": 631, "user": "user18", "title": "LoadTest Alarm", "time": 1760315700}, {"id": 632, "user": "user19", "title": "LoadTest Alarm", "time": 1760229360}, {"id": 633, "user": "user21", "title": "LoadTest Alarm", "time": 1760315700}, {"id": 634, "user": "user15", "title": "LoadTest Alarm", "time": 1760229360}, {"id": 635, "user": "user37", "title": "LoadTest Alarm", "time": 1760315700}, {"id": 636, "user": "user39", "title": "LoadTest Alarm", "time": 1760229420}, {"id": 637, "user": "user1", "title": "LoadTest Alarm", "time": 1760229360}, {"id": 638, "user": "user20", "title": "LoadTest Alarm", "time": 1760229420}, {"id": 639, "user": "user45", "title": "LoadTest Alarm", "time": 1760229360}, {"id": 640, "user": "user41", "title": "LoadTest Alarm", "time": 1760229420}, {"id": 641, "user": "user10", "title": "LoadTest Alarm", "time": 1760229360}, {"id": 642, "user": "user46", "title": "LoadTest Alarm", "time": 1760315700}, {"id": 643, "user": "user3", "title": "LoadTest Alarm", "time": 1760229420}, {"id": 644, "user": "user27", "title": "LoadTest Alarm", "time": 1760229360}, {"id": 645, "user": "user42", "title": "LoadTest Alarm", "time": 1760229420}, {"id": 646, "user": "user45", "title": "LoadTest Alarm", "time": 1760229360}, {"id": 647, "user": "user36", "title": "LoadTest Alarm", "time": 1760229360}, {"id": 648, "user": "user12", "title": "LoadTest Alarm", "time": 1760229360}, {"id": 649, "user": "user31", "title": "LoadTest Alarm", "time": 1760229420}, {"id": 650, "user": "user10", "title": "LoadTest Alarm", "time": 1760229420}, {"id": 651, "user": "user42", "title": "LoadTest Alarm", "time": 1760229480}, {"id": 652, "user": "user7", "title": "LoadTest Alarm", "time": 1760229420}, {"id": 653, "user": "user19", "title": "LoadTest Alarm", "time": 1760229480}, {"id": 654, "user": "user27", "title": "LoadTest Alarm", "time": 1760315700}, {"id": 655, "user": "user34", "title": "LoadTest Alarm", "time": 1760315700}, {"id": 656, "user": "user20", "title": "LoadTest Alarm", "time": 1760229360}, {"id": 657, "user": "user48", "title": "LoadTest Alarm", "time": 1760315700}, {"id": 658, "user": "user35", "title": "LoadTest Alarm", "time": 1760229360}, {"id": 659, "user": "user20", "title": "LoadTest Alarm", "time": 1760229480}, {"id": 660, "user": "user42", "title": "LoadTest Alarm", "time": 1760315700}, {"id": 661, "user": "user31", "title": "LoadTest Alarm", "time": 1760229480}, {"id": 662, "user": "user40", "title": "LoadTest Alarm", "time": 1760315700}, {"id": 663, "user": "user35", "title": "LoadTest Alarm", "time": 1760315700}, {"id": 664, "user": "user45", "title": "LoadTest Alarm", "time": 1760229420}, {"id": 665, "user": "user1", "title": "LoadTest Alarm", "time": 1760229360}, {"id": 666, "user": "user8", "title": "LoadTest Alarm", "time": 1760229360}, {"id": 667, "user": "user43", "title": "LoadTest Alarm", "time": 1760229360}, {"id": 668, "user": "user40", "title": "LoadTest Alarm", "time": 1760229360}, {"id": 669, "user": "user46", "title": "LoadTest Alarm", "time": 1760229420}, {"id": 670, "user": "user38", "title": "LoadTest Alarm", "time": 1760229360}, {"id": 671, "user": "user31", "title": "LoadTest Alarm", "time": 1760229480}, {"id": 672, "user": "user36", "title": "LoadTest Alarm", "time": 1760315700}, {"id": 673, "user": "user41", "title": "LoadTest Alarm", "time": 1760229420}, {"id": 674, "user": "user41", "title": "LoadTest Alarm", "time": 1760229360}, {"id": 675, "user": "user15", "title": "LoadTest Alarm", "time": 1760229420}, {"id": 676, "user": "user8", "title": "LoadTest Alarm", "time": 1760229360}, {"id": 677, "user": "user42", "title": "LoadTest Alarm", "time": 1760229480}, {"id": 678, "user": "user47", "title": "LoadTest Alarm", "time": 1760229480}, {"id": 679, "user": "user11", "title": "LoadTest Alarm", "time": 1760229420}, {"id": 680, "user": "user12", "title": "LoadTest Alarm", "time": 1760229360}, {"id": 681, "user": "user48", "title": "LoadTest Alarm", "time": 1760229420}, {"id": 682, "user": "user22", "title": "LoadTest Alarm", "time": 1760229360}, {"id": 683, "user": "user39", "title": "LoadTest Alarm", "time": 1760229360}, {"id": 684, "user": "user41", "title": "LoadTest Alarm", "time": 1760229360}, {"id": 685, "user": "user11", "title": "LoadTest Alarm", "time": 1760229360}, {"id": 686, "user": "user49", "title": "LoadTest Alarm", "time": 1760229360}, {"id": 687, "user": "user25", "title": "LoadTest Alarm", "time": 1760229360}, {"id": 688, "user": "user35", "title": "LoadTest Alarm", "time": 1760229420}, {"id": 689, "user": "user31", "title": "LoadTest Alarm", "time": 1760229360}, {"id": 690, "user": "user49", "title": "LoadTest Alarm", "time": 1760315700}, {"id": 691, "user": "user13", "title": "LoadTest Alarm", "time": 1760229360}, {"id": 692, "user": "user32", "title": "LoadTest Alarm", "time": 1760315700}, {"id": 693, "user": "user18", "title": "LoadTest Alarm", "time": 1760229480}, {"id": 694, "user": "user40", "title": "LoadTest Alarm", "time": 1760315700}, {"id": 695, "user": "user13", "title": "LoadTest Alarm", "time": 1760315700}, {"id": 696, "user": "user19", "title": "LoadTest Alarm", "time": 1760315700}, {"id": 697, "user": "user24", "title": "LoadTest Alarm", "time": 1760229360}, {"id": 698, "user": "user22", "title": "LoadTest Alarm", "time": 1760229360}, {"id": 699, "user": "user16", "title": "LoadTest Alarm", "time": 1760229420}, {"id": 700, "user": "user22", "title": "LoadTest Alarm", "time": 1760229420}, {"id": 701, "user": "user24", "title": "LoadTest Alarm", "time": 1760229360}, {"id": 702, "user": "user44", "title": "LoadTest Alarm", "time": 1760229420}, {"id": 703, "user": "user38", "title": "LoadTest Alarm", "time": 1760229420}, {"id": 704, "user": "user41", "title": "LoadTest Alarm", "time": 1760229420}, {"id": 705, "user": "user42", "title": "LoadTest Alarm", "time": 1760229360}, {"id": 706, "user": "user27", "title": "LoadTest Alarm", "time": 1760229420}, {"id": 707, "user": "user2", "title": "LoadTest Alarm", "time": 1760315700}, {"id": 708, "user": "user5", "title": "LoadTest Alarm", "time": 1760229420}, {"id": 709, "user": "user32", "title": "LoadTest Alarm", "time": 1760229420}, {"id": 710, "user": "user33", "title": "LoadTest Alarm", "time": 1760229480}, {"id": 711, "user": "user13", "title": "LoadTest Alarm", "time": 1760229420}, {"id": 712, "user": "user30", "title": "LoadTest Alarm", "time": 1760229420}, {"id": 713, "user": "user18", "title": "LoadTest Alarm", "time": 1760315700}, {"id": 714, "user": "user41", "title": "LoadTest Alarm", "time": 1760229360}, {"id": 715, "user": "user34", "title": "LoadTest Alarm", "time": 1760315700}, {"id": 716, "user": "user14", "title": "LoadTest Alarm", "time": 1760229420}, {"id": 717, "user": "user6", "title": "LoadTest Alarm", "time": 1760229420}, {"id": 718, "user": "user9", "title": "LoadTest Alarm", "time": 1760229360}, {"id": 719, "user": "user40", "title": "LoadTest Alarm", "time": 1760315700}, {"id": 720, "user": "user15", "title": "LoadTest Alarm", "time": 1760229420}, {"id": 721, "user": "user24", "title": "LoadTest Alarm", "time": 1760229360}, {"id": 722, "user": "user40", "title": "LoadTest Alarm", "time": 1760315700}, {"id": 723, "user": "user44", "title": "LoadTest Alarm", "time": 1760315700}, {"id": 724, "user": "user30", "title": "LoadTest Alarm", "time": 1760229480}, {"id": 725, "user": "user42", "title": "LoadTest Alarm", "time": 1760229360}, {"id": 726, "user": "user24", "title": "LoadTest Alarm", "time": 1760229420}, {"id": 727, "user": "user38", "title": "LoadTest Alarm", "time": 1760229480}, {"id": 728, "user": "user36", "title": "LoadTest Alarm", "time": 1760315700}, {"id": 729, "user": "user42", "title": "LoadTest Alarm", "time": 1760315700}, {"id": 730, "user": "user48", "title": "LoadTest Alarm", "time": 1760229420}, {"id": 731, "user": "user34", "title": "LoadTest Alarm", "time": 1760229360}, {"id": 732, "user": "user36", "title": "LoadTest Alarm", "time": 1760229420}, {"id": 733, "user": "user19", "title": "LoadTest Alarm", "time": 1760229420}, {"id": 734, "user": "user41", "title": "LoadTest Alarm", "time": 1760315700}, {"id": 735, "user": "user50", "title": "LoadTest Alarm", "time": 1760229480}, {"id": 736, "user": "user37", "title": "LoadTest Alarm", "time": 1760229480}, {"id": 737, "user": "user36", "title": "LoadTest Alarm", "time": 1760229480}, {"id": 738, "user": "user44", "title": "LoadTest Alarm", "time": 1760229420}, {"id": 739, "user": "user4", "title": "LoadTest Alarm", "time": 1760229420}, {"id": 740, "user": "user42", "title": "LoadTest Alarm", "time": 1760229480}, {"id": 741, "user": "user45", "title": "LoadTest Alarm", "time": 1760229360}, {"id": 742, "user": "user23", "title": "LoadTest Alarm", "time": 1760229420}, {"id": 743, "user": "user36", "title": "LoadTest Alarm", "time": 1760229420}, {"id": 744, "user": "user36", "title": "LoadTest Alarm", "time": 1760229420}, {"id": 745, "user": "user36", "title": "LoadTest Alarm", "time": 1760229480}, {"id": 746, "user": "user33", "title": "LoadTest Alarm", "time": 1760229360}, {"id": 747, "user": "user3", "title": "LoadTest Alarm", "time": 1760315700}, {"id": 748, "user": "user2", "title": "LoadTest Alarm", "time": 1760229480}, {"id": 749, "user": "user1", "title": "LoadTest Alarm", "time": 1760229480}, {"id": 750, "user": "user2", "title": "LoadTest Alarm", "time": 1760229360}, {"id": 751, "user": "user34", "title": "LoadTest Alarm", "time": 1760229360}, {"id": 752, "user": "user46", "title": "LoadTest Alarm", "time": 1760229360}, {"id": 753, "user": "user15", "title": "LoadTest Alarm", "time": 1760229360}, {"id": 754, "user": "user8", "title": "LoadTest Alarm", "time": 1760229420}, {"id": 755, "user": "user28", "title": "LoadTest Alarm", "time": 1760229360}, {"id": 756, "user": "user32", "title": "LoadTest Alarm", "time": 1760229420}, {"id": 757, "user": "user40", "title": "LoadTest Alarm", "time": 1760229420}, {"id": 758, "user": "user36", "title": "LoadTest Alarm", "time": 1760229360}, {"id": 759, "user": "user21", "title": "LoadTest Alarm", "time": 1760229420}, {"id": 760, "user": "user22", "title": "LoadTest Alarm", "time": 1760229480}, {"id": 761, "user": "user31", "title": "LoadTest Alarm", "time": 1760229420}, {"id": 762, "user": "user35", "title": "LoadTest Alarm", "time": 1760229420}, {"id": 763, "user": "user27", "title": "LoadTest Alarm", "time": 1760315700}, {"id": 764, "user": "user12", "title": "LoadTest Alarm", "time": 1760229420}, {"id": 765, "user": "user49", "title": "LoadTest Alarm", "time": 1760229480}, {"id": 766, "user": "user24", "title": "LoadTest Alarm", "time": 1760229420}, {"id": 767, "user": "user6", "title": "LoadTest Alarm", "time": 1760229480}, {"id": 768, "user": "user42", "title": "LoadTest Alarm", "time": 1760229360}, {"id": 769, "user": "user41", "title": "LoadTest Alarm", "time": 1760229360}, {"id": 770, "user": "user46", "title": "LoadTest Alarm", "time": 1760229480}, {"id": 771, "user": "user48", "title": "LoadTest Alarm", "time": 1760229360}, {"id": 772, "user": "user44", "title": "LoadTest Alarm", "time": 1760229480}, {"id": 773, "user": "user42", "title": "LoadTest Alarm", "time": 1760229420}, {"id": 774, "user": "user25", "title": "LoadTest Alarm", "time": 1760229480}, {"id": 775, "user": "user50", "title": "LoadTest Alarm", "time": 1760229360}, {"id": 776, "user": "user40", "title": "LoadTest Alarm", "time": 1760229420}, {"id": 777, "user": "user30", "title": "LoadTest Alarm", "time": 1760229420}, {"id": 778, "user": "user17", "title": "LoadTest Alarm", "time": 1760229360}, {"id": 779, "user": "user18", "title": "LoadTest Alarm", "time": 1760315700}, {"id": 780, "user": "user18", "title": "LoadTest Alarm", "time": 1760229420}, {"id": 781, "user": "user33", "title": "LoadTest Alarm", "time": 1760229360}, {"id": 782, "user": "user4", "title": "LoadTest Alarm", "time": 1760229420}, {"id": 783, "user": "user9", "title": "LoadTest Alarm", "time": 1760229420}, {"id": 784, "user": "user24", "title": "LoadTest Alarm", "time": 1760229360}, {"id": 785, "user": "user16", "title": "LoadTest Alarm", "time": 1760229360}, {"id": 786, "user": "user25", "title": "LoadTest Alarm", "time": 1760229420}, {"id": 787, "user": "user47", "title": "LoadTest Alarm", "time": 1760229420}, {"id": 788, "user": "user4", "title": "LoadTest Alarm", "time": 1760229480}, {"id": 789, "user": "user45", "title": "LoadTest Alarm", "time": 1760229360}, {"id": 790, "user": "user50", "title": "LoadTest Alarm", "time": 1760229480}, {"id": 791, "user": "user23", "title": "LoadTest Alarm", "time": 1760229420}, {"id": 792, "user": "user12", "title": "LoadTest Alarm", "time": 1760315760}, {"id": 793, "user": "user2", "title": "LoadTest Alarm", "time": 1760229420}, {"id": 794, "user": "user9", "title": "LoadTest Alarm", "time": 1760315760}, {"id": 795, "user": "user21", "title": "LoadTest Alarm", "time": 1760315760}, {"id": 796, "user": "user15", "title": "LoadTest Alarm", "time": 1760229480}, {"id": 797, "user": "user20", "title": "LoadTest Alarm", "time": 1760229420}, {"id": 798, "user": "user43", "title": "LoadTest Alarm", "time": 1760229420}, {"id": 799, "user": "user40", "title": "LoadTest Alarm", "time": 1760315760}, {"id": 800, "user": "user50", "title": "LoadTest Alarm", "time": 1760229480}, {"id": 801, "user": "user45", "title": "LoadTest Alarm", "time": 1760229480}, {"id": 802, "user": "user39", "title": "LoadTest Alarm", "time": 1760229420}, {"id": 803, "user": "user16", "title": "LoadTest Alarm", "time": 1760229480}, {"id": 804, "user": "user49", "title": "LoadTest Alarm", "time": 1760229480}, {"id": 805, "user": "user7", "title": "LoadTest Alarm", "time": 1760315700}, {"id": 806, "user": "user30", "title": "LoadTest Alarm", "time": 1760229420}, {"id": 807, "user": "user20", "title": "LoadTest Alarm", "time": 1760229420}, {"id": 808, "user": "user7", "title": "LoadTest Alarm", "time": 1760229480}, {"id": 809, "user": "user13", "title": "LoadTest Alarm", "time": 1760315760}, {"id": 810, "user": "user40", "title": "LoadTest Alarm", "time": 1760315760}, {"id": 811, "user": "user24", "title": "LoadTest Alarm", "time": 1760315760}, {"id": 812, "user": "user24", "title": "LoadTest Alarm", "time": 1760229420}, {"id": 813, "user": "user36", "title": "LoadTest Alarm", "time": 1760229480}, {"id": 814, "user": "user34", "title": "LoadTest Alarm", "time": 1760229480}, {"id": 815, "user": "user19", "title": "LoadTest Alarm", "time": 1760229420}, {"id": 816, "user": "user1", "title": "LoadTest Alarm", "time": 1760229480}, {"id": 817, "user": "user47", "title": "LoadTest Alarm", "time": 1760315760}, {"id": 818, "user": "user31", "title": "LoadTest Alarm", "time": 1760229420}, {"id": 819, "user": "user7", "title": "LoadTest Alarm", "time": 1760229420}, {"id": 820, "user": "user6", "title": "LoadTest Alarm", "time": 1760315760}, {"id": 821, "user": "user23", "title": "LoadTest Alarm", "time": 1760315760}, {"id": 822, "user": "user8", "title": "LoadTest Alarm", "time": 1760229480}, {"id": 823, "user": "user50", "title": "LoadTest Alarm", "time": 1760229420}, {"id": 824, "user": "user34", "title": "LoadTest Alarm", "time": 1760229420}, {"id": 825, "user": "user8", "title": "LoadTest Alarm", "time": 1760229420}, {"id": 826, "user": "user50", "title": "LoadTest Alarm", "time": 1760229420}, {"id": 827, "user": "user31", "title": "LoadTest Alarm", "time": 1760229480}, {"id": 828, "user": "user2", "title": "LoadTest Alarm", "time": 1760315760}, {"id": 829, "user": "user23", "title": "LoadTest Alarm", "time": 1760315760}, {"id": 830, "user": "user42", "title": "LoadTest Alarm", "time": 1760315760}, {"id": 831, "user": "user3", "title": "LoadTest Alarm", "time": 1760229420}, {"id": 832, "user": "user42", "title": "LoadTest Alarm", "time": 1760229420}, {"id": 833, "user": "user19", "title": "LoadTest Alarm", "time": 1760229420}, {"id": 834, "user": "user4", "title": "LoadTest Alarm", "time": 1760315760}, {"id": 835, "user": "user8", "title": "LoadTest Alarm", "time": 1760315760}, {"id": 836, "user": "user36", "title": "LoadTest Alarm", "time": 1760315760}, {"id": 837, "user": "user32", "title": "LoadTest Alarm", "time": 1760315760}, {"id": 838, "user": "user50", "title": "LoadTest Alarm", "time": 1760229480}, {"id": 839, "user": "user45", "title": "LoadTest Alarm", "time": 1760229420}, {"id": 840, "user": "user42", "title": "LoadTest Alarm", "time": 1760229480}, {"id": 841, "user": "user19", "title": "LoadTest Alarm", "time": 1760315760}, {"id": 842, "user": "user33", "title": "LoadTest Alarm", "time": 1760229420}, {"id": 843, "user": "user31", "title": "LoadTest Alarm", "time": 1760315700}, {"id": 844, "user": "user23", "title": "LoadTest Alarm", "time": 1760315760}, {"id": 845, "user": "user23", "title": "LoadTest Alarm", "time": 1760229420}, {"id": 846, "user": "user35", "title": "LoadTest Alarm", "time": 1760229420}, {"id": 847, "user": "user29", "title": "LoadTest Alarm", "time": 1760229420}, {"id": 848, "user": "user33", "title": "LoadTest Alarm", "time": 1760315760}, {"id": 849, "user": "user36", "title": "LoadTest Alarm", "time": 1760229420}, {"id": 9, "user": "", "title": "Updated Alarm 9", "time": 1760315760}, {"id": 850, "user": "user19", "title": "LoadTest Alarm", "time": 1760315760}, {"id": 851, "user": "user40", "title": "LoadTest Alarm", "time": 1760229420}, {"id": 10, "user": "", "title": "Updated Alarm 10", "time": 1760315760}, {"id": 852, "user": "user47", "title": "LoadTest Alarm", "time": 1760315760}, {"id": 853, "user": "user9", "title": "LoadTest Alarm", "time": 1760315760}, {"id": 854, "user": "user49", "title": "LoadTest Alarm", "time": 1760229480}, {"id": 855, "user": "user32", "title": "LoadTest Alarm", "time": 1760315760}, {"id": 856, "user": "user31", "title": "LoadTest Alarm", "time": 1760315760}, {"id": 857, "user": "user22", "title": "LoadTest Alarm", "time": 1760229480}, {"id": 858, "user": "user4", "title": "LoadTest Alarm", "time": 1760229420}, {"id": 859, "user": "user26", "title": "LoadTest Alarm", "time": 1760315760}, {"id": 860, "user": "user7", "title": "LoadTest Alarm", "time": 1760315760}, {"id": 861, "user": "user6", "title": "LoadTest Alarm", "time": 1760315760}, {"id": 17, "user": "", "title": "Updated Alarm 17", "time": 1760229420}, {"id": 862, "user": "user10", "title": "LoadTest Alarm", "time": 1760229480}, {"id": 863, "user": "user10", "title": "LoadTest Alarm", "time": 1760229480}, {"id": 864, "user": "user13", "title": "LoadTest Alarm", "time": 1760229480}, {"id": 865, "user": "user15", "title": "LoadTest Alarm", "time": 1760315760}, {"id": 866, "user": "user13", "title": "LoadTest Alarm", "time": 1760229420}, {"id": 867, "user": "user44", "title": "LoadTest Alarm", "time": 1760229480}, {"id": 868, "user": "user26", "title": "LoadTest Alarm", "time": 1760229480}, {"id": 869, "user": "user6", "title": "LoadTest Alarm", "time": 1760229480}, {"id": 870, "user": "user41", "title": "LoadTest Alarm", "time": 1760315760}, {"id": 871, "user": "user40", "title": "LoadTest Alarm", "time": 1760229420}, {"id": 872, "user": "user30", "title": "LoadTest Alarm", "time": 1760229420}, {"id": 873, "user": "user22", "title": "LoadTest Alarm", "time": 1760229480}, {"id": 874, "user": "user19", "title": "LoadTest Alarm", "time": 1760315760}, {"id": 875, "user": "user46", "title": "LoadTest Alarm", "time": 1760315760}, {"id": 876, "user": "user44", "title": "LoadTest Alarm", "time": 1760229480}, {"id": 19, "user": "", "title": "Updated Alarm 19", "time": 1760315760}, {"id": 14, "user": "", "title": "Updated Alarm 14", "time": 1760229420}, {"id": 877, "user": "user30", "title": "LoadTest Alarm", "time": 1760229420}, {"id": 4, "user": "", "title": "Updated Alarm 4", "time": 1760229420}, {"id": 878, "user": "user3", "title": "LoadTest Alarm", "time": 1760229420}, {"id": 879, "user": "user19", "title": "LoadTest Alarm", "time": 1760229480}, {"id": 880, "user": "user22", "title": "LoadTest Alarm", "time": 1760229420}, {"id": 881, "user": "user43", "title": "LoadTest Alarm", "time": 1760315760}, {"id": 7, "user": "", "title": "Updated Alarm 7", "time": 1760315760}, {"id": 882, "user": "user49", "title": "LoadTest Alarm", "time": 1760229540}, {"id": 883, "user": "user9", "title": "LoadTest Alarm", "time": 1760229480}, {"id": 884, "user": "user39", "title": "LoadTest Alarm", "time": 1760315760}, {"id": 885, "user": "user43", "title": "LoadTest Alarm", "time": 1760315760}, {"id": 886, "user": "user15", "title": "LoadTest Alarm", "time": 1760315760}, {"id": 887, "user": "user11", "title": "LoadTest Alarm", "time": 1760229420}, {"id": 888, "user": "user29", "title": "LoadTest Alarm", "time": 1760229420}, {"id": 889, "user": "user23", "title": "LoadTest Alarm", "time": 1760229420}, {"id": 890, "user": "user49", "title": "LoadTest Alarm", "time": 1760229420}, {"id": 891, "user": "user13", "title": "LoadTest Alarm", "time": 1760229540}, {"id": 892, "user": "user26", "title": "LoadTest Alarm", "time": 1760315760}, {"id": 893, "user": "user33", "title": "LoadTest Alarm", "time": 1760229540}, {"id": 6, "user": "", "title": "Updated Alarm 6", "time": 1760229420}, {"id": 5, "user": "", "title": "Updated Alarm 5", "time": 1760315760}, {"id": 894, "user": "user24", "title": "LoadTest Alarm", "time": 1760229480}, {"id": 895, "user": "user16", "title": "LoadTest Alarm", "time": 1760229420}, {"id": 15, "user": "", "title": "Updated Alarm 15", "time": 1760229480}, {"id": 896, "user": "user42", "title": "LoadTest Alarm", "time": 1760315760}, {"id": 897, "user": "user24", "title": "LoadTest Alarm", "time": 1760229420}, {"id": 13, "user": "", "title": "Updated Alarm 13", "time": 1760315760}, {"id": 898, "user": "user15", "title": "LoadTest Alarm", "time": 1760229420}, {"id": 8, "user": "", "title": "Updated Alarm 8", "time": 1760229480}]